grapheneapi/__init__.py
grapheneapi/exceptions.py
grapheneapi/grapheneapi.py
grapheneapi/grapheneclient.py
grapheneapi/graphenehttprpc.py
grapheneapi/graphenews.py
grapheneapi/graphenewsprotocol.py
grapheneapi/graphenewsrpc.py
graphenebase/__init__.py
graphenebase/account.py
graphenebase/base58.py
graphenebase/bip38.py
graphenebase/chains.py
graphenebase/dictionary.py
graphenebase/ecdsa.py
graphenebase/objects.py
graphenebase/objecttypes.py
graphenebase/operationids.py
graphenebase/operations.py
graphenebase/signedtransactions.py
graphenebase/transactions.py
graphenebase/types.py
pygraphenelib-0.5.3.dist-info/DESCRIPTION.rst
pygraphenelib-0.5.3.dist-info/METADATA
pygraphenelib-0.5.3.dist-info/RECORD
pygraphenelib-0.5.3.dist-info/WHEEL
pygraphenelib-0.5.3.dist-info/metadata.json
pygraphenelib-0.5.3.dist-info/top_level.txt
