Metadata-Version: 2.0
Name: pygraphenelib
Version: 0.5.3
Summary: Python library for graphene-based blockchains
Home-page: http://pygraphenelib
Author: Starry Zhang
Author-email: 463834772@qq.com
License: UNKNOWN
Download-URL: http://pygraphenelib0.5.3
Keywords: graphene,api,rpc,ecdsa,secp256k1
Platform: UNKNOWN
Classifier: License :: OSI Approved :: MIT License
Classifier: Operating System :: OS Independent
Classifier: Programming Language :: Python :: 3
Classifier: Development Status :: 3 - Alpha
Classifier: Intended Audience :: Developers
Requires-Dist: ecdsa
Requires-Dist: pycryptodome
Requires-Dist: pylibscrypt
Requires-Dist: requests
Requires-Dist: websocket-client
